pytedee_async/__init__.py
pytedee_async/bridge.py
pytedee_async/const.py
pytedee_async/exception.py
pytedee_async/helpers.py
pytedee_async/lock.py
pytedee_async/py.typed
pytedee_async/tedee_client.py
pytedee_async-0.2.20.dist-info/LICENSE
pytedee_async-0.2.20.dist-info/METADATA
pytedee_async-0.2.20.dist-info/WHEEL
pytedee_async-0.2.20.dist-info/top_level.txt
pytedee_async-0.2.20.dist-info/RECORD
