Metadata-Version: 2.1
Name: pytedee_async
Version: 0.2.20
Summary: A Tedee Lock Client package
Home-page: https://github.com/zweckj/pytedee_async
Author: Josef Zweck
Author-email: 24647999+zweckj@users.noreply.github.com
License: MIT
Classifier: Development Status :: 3 - Alpha
Classifier: Intended Audience :: Developers
Classifier: Natural Language :: English
Classifier: Programming Language :: Python :: 3
Classifier: License :: OSI Approved :: MIT License
Classifier: Operating System :: OS Independent
Requires-Python: >=3.9
License-File: LICENSE
Requires-Dist: aiohttp
